convert_us_to_uk/__init__.py
convert_us_to_uk/converter.py
convert_us_to_uk/us_to_uk_trans.csv
convert_us_to_uk-0.1.9.dist-info/METADATA
convert_us_to_uk-0.1.9.dist-info/WHEEL
convert_us_to_uk-0.1.9.dist-info/entry_points.txt
convert_us_to_uk-0.1.9.dist-info/top_level.txt
convert_us_to_uk-0.1.9.dist-info/RECORD
