Metadata-Version: 2.1
Name: convert-us-to-uk
Version: 0.1.9
Summary: A simple utility to convert US spelling to UK spelling.
Home-page: https://github.com/oliverblane/convert-us-to-uk/tree/main
Author: Oliver Blane
Author-email: oliverblane72@gmail.com
Requires-Python: >=3.10
